dcs_scripts/__init__.py
dcs_scripts/cli.py
dcs_scripts/constants.py
dcs_scripts/utils.py
dcs_scripts/wound_healing_utils.py
dcs_scripts-1.2.0.dist-info/METADATA
dcs_scripts-1.2.0.dist-info/WHEEL
dcs_scripts-1.2.0.dist-info/entry_points.txt
dcs_scripts-1.2.0.dist-info/RECORD
