Metadata-Version: 2.1
Name: dcs-scripts
Version: 1.2.0
Summary: Helper scripts for Draycon Cell Segmentation (dcs) workflows
License: MIT
Author: Arun Nemani
Author-email: neman014@gmail.com
Requires-Python: >=3.9,<3.12
Classifier: License :: OSI Approved :: MIT License
Classifier: Programming Language :: Python :: 3
Classifier: Programming Language :: Python :: 3.9
Classifier: Programming Language :: Python :: 3.10
Classifier: Programming Language :: Python :: 3.11
Requires-Dist: azure-batch (>=14.2.0,<15.0.0)
Requires-Dist: azure-identity (>=1.16.0,<2.0.0)
Requires-Dist: azure-keyvault-secrets (>=4.8.0,<5.0.0)
Requires-Dist: azure-storage-blob (>=12.20.0,<13.0.0)
Requires-Dist: matplotlib (<3.9)
Requires-Dist: pandas (<2.0)
Requires-Dist: pyyaml (>=6.0.1,<7.0.0)
Requires-Dist: requests (>=2.25.1,<3.0.0)
Requires-Dist: seaborn (<0.12)
Requires-Dist: statannotations (>=0.6.0,<0.7.0)
